staff_ocr/__init__.py
staff_ocr/angnet/__init__.py
staff_ocr/angnet/angle.py
staff_ocr/crnn/__init__.py
staff_ocr/crnn/CRNN.py
staff_ocr/crnn/keys.py
staff_ocr/crnn/util.py
staff_ocr/dbnet/__init__.py
staff_ocr/dbnet/dbnet_infer.py
staff_ocr/dbnet/decode.py
staff_ocr/dbnet/test.jpg
staff_ocr/model.py
staff_ocr/ocr.py
staff_ocr/setting.py
staff_ocr/util/__init__.py
staff_ocr/util/common_util.py
staff_ocr/util/io_util.py
staff_ocr-1.0.3.dist-info/WHEEL
staff_ocr-1.0.3.dist-info/METADATA
staff_ocr-1.0.3.dist-info/RECORD
