Metadata-Version: 2.1
Name: staff-ocr
Version: 1.0.3
Summary: 
Author: JimZhang
Author-email: zzl22100048@gmail.com
Requires-Python: >=3.7,<4.0
Classifier: Programming Language :: Python :: 3
Classifier: Programming Language :: Python :: 3.7
Classifier: Programming Language :: Python :: 3.8
Classifier: Programming Language :: Python :: 3.9
Requires-Dist: hanlp-downloader (>=0.0.22,<0.1.0)
Requires-Dist: loguru (>=0.5.3,<0.6.0)
Requires-Dist: numpy (>=1.19.5,<2.0.0)
Requires-Dist: onnxruntime (>=1.8.0,<1.9.0)
Requires-Dist: opencv-python (>=4.5.2,<4.6.0)
Requires-Dist: pillow (>=8.2.0,<8.3.0)
Requires-Dist: pyclipper (>=1.2.1,<2.0.0)
Requires-Dist: shapely (>=1.7.1,<2.0.0)
Requires-Dist: termcolor (>=1.1.0,<1.2.0)
